[
    {
        "path": "404.html",
        "type": "file",
        "md5": "209f827f062d48af6c8083eb6bca4a2e"
    },
    {
        "path": "assets",
        "type": "directory",
        "md5": false
    },
    {
        "path": "assets/css",
        "type": "directory",
        "md5": false
    },
    {
        "path": "/assets/css/editor.css",
        "type": "file",
        "md5": "4202808df745f2ac7ab250606fa0d272"
    },
    {
        "path": "/assets/css/main.css",
        "type": "file",
        "md5": "fa238f48f9a2ab93b0c59a116e831bca"
    },
    {
        "path": "/assets/css/style.css",
        "type": "file",
        "md5": "11bee19e86e8eda2cf9a60efd975666d"
    },
    {
        "path": "assets/dynamic",
        "type": "directory",
        "md5": false
    },
    {
        "path": "assets/js",
        "type": "directory",
        "md5": false
    },
    {
        "path": "/assets/js/scripts.js",
        "type": "file",
        "md5": "e9e5c3efbaa696d1490988cf5b30e23b"
    },
    {
        "path": "/assets/js/scripts.min.js",
        "type": "file",
        "md5": "700105c316933a8202041b6415abb233"
    },
    {
        "path": "/assets/js/svg-fix.js",
        "type": "file",
        "md5": "9b7d020c55e2b4f77ab40c97f88f9ff4"
    },
    {
        "path": "/assets/js/svg-map.js",
        "type": "file",
        "md5": "ff4392540fcf4c3d3f5e03806e112816"
    },
    {
        "path": "assets/svg",
        "type": "directory",
        "md5": false
    },
    {
        "path": "/assets/svg/svg-map.svg",
        "type": "file",
        "md5": "cf04dfd5c3cc64e0be44692fe7d976a6"
    },
    {
        "path": "authors",
        "type": "directory",
        "md5": false
    },
    {
        "path": "authors/heba",
        "type": "directory",
        "md5": false
    },
    {
        "path": "/authors/heba/index.html",
        "type": "file",
        "md5": "8455800519aa9921764bca617a228813"
    },
    {
        "path": "feed.json",
        "type": "file",
        "md5": "4bac6371e254e9400755705fddddf601"
    },
    {
        "path": "feed.xml",
        "type": "file",
        "md5": "d25ce950304d1fe3293f015029c9da1d"
    },
    {
        "path": "hmy-mkfh-hshrt-fy-lshrq",
        "type": "directory",
        "md5": false
    },
    {
        "path": "/hmy-mkfh-hshrt-fy-lshrq/index.html",
        "type": "file",
        "md5": "2582fd633dd0cf5b48b7b85277932666"
    },
    {
        "path": "index.html",
        "type": "file",
        "md5": "49f589dc4ff4b98df44f5bdb3e7dd782"
    },
    {
        "path": "mkfh-hshrt-fy-lshrq-lhl-lmthl-lltkhls-mn-lhshrt-nhyyan",
        "type": "directory",
        "md5": false
    },
    {
        "path": "/mkfh-hshrt-fy-lshrq-lhl-lmthl-lltkhls-mn-lhshrt-nhyyan/index.html",
        "type": "file",
        "md5": "3d80c147745ff5bf077a6f6c5c1afaf5"
    },
    {
        "path": "nsyh-llwqy-mn-lhshrt-baad-lmkfh",
        "type": "directory",
        "md5": false
    },
    {
        "path": "/nsyh-llwqy-mn-lhshrt-baad-lmkfh/index.html",
        "type": "file",
        "md5": "672fdee44c6d253aa789fac5ff6225e9"
    },
    {
        "path": "robots.txt",
        "type": "file",
        "md5": "794e0aa7d4701cbe3aa8745ef5f9e7f4"
    },
    {
        "path": "sitemap.xml",
        "type": "file",
        "md5": "f0cb17e0530f58405923613da717632c"
    },
    {
        "path": "sitemap.xsl",
        "type": "file",
        "md5": "03c2f9a7fdcc46ff05c435907614a0b8"
    },
    {
        "path": "tags",
        "type": "directory",
        "md5": false
    },
    {
        "path": "/tags/index.html",
        "type": "file",
        "md5": "36ef1920bd2c4a365f70676afbbd124e"
    }
]